RoboCam/__init__.py
RoboCam/aruco_detector.py
RoboCam/face_detector.py
RoboCam/face_landmark.py
RoboCam/face_recognizer.py
RoboCam/number_recognizer.py
RoboCam/robocam.py
RoboCam/sketch_recognizer.py
RoboCam/res/model/face_detector.tflite
RoboCam/res/model/face_keypoints.tflite
RoboCam/res/model/face_recognizer.tflite
RoboCam/res/model/iris_landmark.tflite
RoboCam/res/model/mnist_model.tflite
RoboCam-1.0.0.34.dist-info/METADATA
RoboCam-1.0.0.34.dist-info/WHEEL
RoboCam-1.0.0.34.dist-info/top_level.txt
RoboCam-1.0.0.34.dist-info/RECORD
