Metadata-Version: 2.1
Name: RoboCam
Version: 1.0.0.34
Summary: Python library for RoboCam
Home-page: https://eng.roborobo.co.kr/main
Download-URL: https://github.com/RoboroboLab/RoboCam/archive/master.tar.gz
Author: Roborobo
Author-email: roborobolab@gmail.com
License: MIT
Keywords: RoboCam,roborobo
Classifier: Programming Language :: Python :: 3
Classifier: Programming Language :: Python :: 3.2
Classifier: Programming Language :: Python :: 3.3
Classifier: Programming Language :: Python :: 3.4
Classifier: Programming Language :: Python :: 3.5
Classifier: Programming Language :: Python :: 3.6
Classifier: Programming Language :: Python :: 3.7
Classifier: Programming Language :: Python :: 3.8
Classifier: Programming Language :: Python :: 3.9
Classifier: Programming Language :: Python :: 3.10
Classifier: Programming Language :: Python :: 3.11
Classifier: Programming Language :: Python :: 3.12
Requires-Python: >=3
Requires-Dist: opencv-contrib-python (==4.7.0.72)
Requires-Dist: tflite (==2.10.0)
Requires-Dist: tensorflow (==2.12.0)
Requires-Dist: numpy (==1.23.5)
